django_auth/__init__.py
django_auth/admin.py
django_auth/apps.py
django_auth/models.py
django_auth/settings.py
django_auth/tests.py
django_auth/urls.py
django_auth/user_validators.py
django_auth/views.py
django_auth/migrations/__init__.py
django_auth/static/css/common.css
django_auth/static/css/index.css
django_auth/static/css/login.css
django_auth/static/css/register.css
django_auth/static/js/common.js
django_auth/static/js/index.js
django_auth/static/js/login.js
django_auth/static/js/register.js
django_auth/static/lib/css/bootstrap-3.3.7.min.css
django_auth/static/lib/css/bootstrap-theme-3.3.7.min.css
django_auth/static/lib/css/bootstrap.min.css.map
django_auth/static/lib/css/normalize-8.0.0.min.css
django_auth/static/lib/css/toastr-2.1.3.min.css
django_auth/static/lib/fonts/element-icons.ttf
django_auth/static/lib/fonts/element-icons.woff
django_auth/static/lib/fonts/glyphicons-halflings-regular.eot
django_auth/static/lib/fonts/glyphicons-halflings-regular.svg
django_auth/static/lib/fonts/glyphicons-halflings-regular.ttf
django_auth/static/lib/fonts/glyphicons-halflings-regular.woff
django_auth/static/lib/fonts/glyphicons-halflings-regular.woff2
django_auth/static/lib/js/bootstrap-3.3.7.min.js
django_auth/static/lib/js/html5shiv.min.js
django_auth/static/lib/js/jquery-3.3.1.min.js
django_auth/static/lib/js/toastr-2.1.3.min.js
django_auth/static/lib/js/toastr.js.map
django_auth/static/lib/js/vue-2.5.13.min.js
django_auth/static/lib/js/vue-lazyload-1.2.3.js
django_auth/templates/django_auth/home/index.html
django_auth/templates/django_auth/layout/base.html
django_auth/templates/django_auth/layout/header.html
django_auth/templates/django_auth/user/header.html
django_auth/templates/django_auth/user/login.html
django_auth/templates/django_auth/user/logout.html
django_auth/templates/django_auth/user/register.html
django_auth/views/__init__.py
django_auth/views/api.py
django_auth/views/base.py
django_auth/views/user.py
django_auth-0.1.9.dist-info/METADATA
django_auth-0.1.9.dist-info/RECORD
django_auth-0.1.9.dist-info/WHEEL
django_auth-0.1.9.dist-info/top_level.txt
